{
   "info": {
      "strategy": "FedYogi",
      "seed": 71,
      "sampling_seed": 71,
      "local_epochs": 3,
      "num_rounds": 10,
      "num_clients": 5,
      "eta": 0.72296,
      "eta_l": 0.16583,
      "iid": true,
      "alpha": null
   },
   "rounds": [
      {
         "round": 0,
         "train_metrics": {},
         "eval_metrics_client": {},
         "eval_metrics_server": {
            "accuracy": 0.375,
            "loss": 0.7110350131988525,
            "f1_score": 0.3731036385064821
         }
      },
      {
         "round": 1,
         "train_metrics": {
            "train_loss": 0.48923940536303395,
            "train_acc": 0.8133333325386046,
            "train_f1": 0.4483025507133721
         },
         "eval_metrics_client": {},
         "eval_metrics_server": {
            "accuracy": 0.8199999928474426,
            "loss": 0.4890581965446472,
            "f1_score": 0.45054945054945056
         }
      },
      {
         "round": 2,
         "train_metrics": {
            "train_loss": 0.5311111628245084,
            "train_acc": 0.7766666611035664,
            "train_f1": 0.43703782977123173
         },
         "eval_metrics_client": {},
         "eval_metrics_server": {
            "accuracy": 0.8199999928474426,
            "loss": 0.33687499165534973,
            "f1_score": 0.45054945054945056
         }
      },
      {
         "round": 3,
         "train_metrics": {
            "train_loss": 0.2620878210052466,
            "train_acc": 0.9399999976158142,
            "train_f1": 0.9084898054227383
         },
         "eval_metrics_client": {},
         "eval_metrics_server": {
            "accuracy": 0.6949999928474426,
            "loss": 0.5432320833206177,
            "f1_score": 0.6386148878817501
         }
      },
      {
         "round": 4,
         "train_metrics": {
            "train_loss": 0.16224304199791872,
            "train_acc": 0.95333331823349,
            "train_f1": 0.925061119015754
         },
         "eval_metrics_client": {},
         "eval_metrics_server": {
            "accuracy": 0.9350000023841858,
            "loss": 0.17125052213668823,
            "f1_score": 0.8993769108711638
         }
      },
      {
         "round": 5,
         "train_metrics": {
            "train_loss": 0.11544716480570151,
            "train_acc": 0.9333333373069763,
            "train_f1": 0.9009685204698206
         },
         "eval_metrics_client": {},
         "eval_metrics_server": {
            "accuracy": 0.8199999928474426,
            "loss": 0.668408989906311,
            "f1_score": 0.76
         }
      },
      {
         "round": 6,
         "train_metrics": {
            "train_loss": 0.1856838137311383,
            "train_acc": 0.9066666762034098,
            "train_f1": 0.8586736720648241
         },
         "eval_metrics_client": {},
         "eval_metrics_server": {
            "accuracy": 0.8849999904632568,
            "loss": 0.43543514609336853,
            "f1_score": 0.8281979458450046
         }
      },
      {
         "round": 7,
         "train_metrics": {
            "train_loss": 0.20843018228277707,
            "train_acc": 0.943333327770233,
            "train_f1": 0.91478214768863
         },
         "eval_metrics_client": {},
         "eval_metrics_server": {
            "accuracy": 0.9449999928474426,
            "loss": 0.20072105526924133,
            "f1_score": 0.9058178860396421
         }
      },
      {
         "round": 8,
         "train_metrics": {
            "train_loss": 0.18412545861941998,
            "train_acc": 0.9566666682561238,
            "train_f1": 0.9383641584846548
         },
         "eval_metrics_client": {},
         "eval_metrics_server": {
            "accuracy": 0.9150000214576721,
            "loss": 0.27256453037261963,
            "f1_score": 0.8707764813196002
         }
      },
      {
         "round": 9,
         "train_metrics": {
            "train_loss": 0.16149847222289118,
            "train_acc": 0.943333347638448,
            "train_f1": 0.8973658209703621
         },
         "eval_metrics_client": {},
         "eval_metrics_server": {
            "accuracy": 0.8399999737739563,
            "loss": 0.511649489402771,
            "f1_score": 0.7400909681611436
         }
      },
      {
         "round": 10,
         "train_metrics": {
            "train_loss": 0.15931226400276405,
            "train_acc": 0.9666666785875955,
            "train_f1": 0.9389785430178668
         },
         "eval_metrics_client": {},
         "eval_metrics_server": {
            "accuracy": 0.9200000166893005,
            "loss": 0.17093168199062347,
            "f1_score": 0.8338870431893688
         }
      }
   ]
}