{
   "info": {
      "strategy": "FedAvg",
      "seed": 87,
      "sampling_seed": 87,
      "fraction_train": 0.75,
      "fraction_evaluate": 0.75,
      "local_epochs": 3,
      "num_rounds": 10,
      "num_clients": 5,
      "eta_l": 0.28242,
      "iid": false,
      "alpha": 1.8,
      "training_mode": "noiseless"
   },
   "rounds": [
      {
         "round": 1,
         "train_metrics": {
            "train_loss": 0.35971200032364903,
            "train_acc": 0.9080882212694954,
            "train_f1": 0.8475732043742907
         },
         "eval_metrics_client": {
            "loss": 0.3666389286518097,
            "accuracy": 0.8749999999999999,
            "f1": 0.8260195466055318
         },
         "eval_metrics_server": {}
      },
      {
         "round": 2,
         "train_metrics": {
            "train_loss": 0.3033133050760579,
            "train_acc": 0.9429530405358181,
            "train_f1": 0.9083975313270914
         },
         "eval_metrics_client": {
            "loss": 0.3082208136717478,
            "accuracy": 0.9449999928474426,
            "f1": 0.9236038891708326
         },
         "eval_metrics_server": {}
      },
      {
         "round": 3,
         "train_metrics": {
            "train_loss": 0.3071324180942726,
            "train_acc": 0.9358974559566913,
            "train_f1": 0.8996866694832765
         },
         "eval_metrics_client": {
            "loss": 0.30914341410001117,
            "accuracy": 0.9399999976158142,
            "f1": 0.9122911455831487
         },
         "eval_metrics_server": {}
      },
      {
         "round": 4,
         "train_metrics": {
            "train_loss": 0.31893897286787787,
            "train_acc": 0.9287671211647661,
            "train_f1": 0.9005965688385003
         },
         "eval_metrics_client": {
            "loss": 0.3061911463737488,
            "accuracy": 0.9416666626930237,
            "f1": 0.9130014112415057
         },
         "eval_metrics_server": {}
      },
      {
         "round": 5,
         "train_metrics": {
            "train_loss": 0.314359562722643,
            "train_acc": 0.9407114648065077,
            "train_f1": 0.9172494886802376
         },
         "eval_metrics_client": {
            "loss": 0.3076731264591217,
            "accuracy": 0.9316666722297668,
            "f1": 0.8985752717318656
         },
         "eval_metrics_server": {}
      },
      {
         "round": 6,
         "train_metrics": {
            "train_loss": 0.29376755604625104,
            "train_acc": 0.9522058887078482,
            "train_f1": 0.9116904225889129
         },
         "eval_metrics_client": {
            "loss": 0.30792326728502906,
            "accuracy": 0.9383333325386047,
            "f1": 0.9116141112743046
         },
         "eval_metrics_server": {}
      },
      {
         "round": 7,
         "train_metrics": {
            "train_loss": 0.30012357087713926,
            "train_acc": 0.9362416217391123,
            "train_f1": 0.9006940852290405
         },
         "eval_metrics_client": {
            "loss": 0.3027668992678324,
            "accuracy": 0.9433333277702332,
            "f1": 0.9206656819145043
         },
         "eval_metrics_server": {}
      },
      {
         "round": 8,
         "train_metrics": {
            "train_loss": 0.30693366869103655,
            "train_acc": 0.9294871812065442,
            "train_f1": 0.8911743692751546
         },
         "eval_metrics_client": {
            "loss": 0.3084767957528432,
            "accuracy": 0.9383333325386047,
            "f1": 0.9097140700440869
         },
         "eval_metrics_server": {}
      },
      {
         "round": 9,
         "train_metrics": {
            "train_loss": 0.31854692944225266,
            "train_acc": 0.9287671211647661,
            "train_f1": 0.9005965688385003
         },
         "eval_metrics_client": {
            "loss": 0.3061611453692118,
            "accuracy": 0.9416666626930237,
            "f1": 0.9130014112415057
         },
         "eval_metrics_server": {}
      },
      {
         "round": 10,
         "train_metrics": {
            "train_loss": 0.3140389540965026,
            "train_acc": 0.9407114648065077,
            "train_f1": 0.9172494886802376
         },
         "eval_metrics_client": {
            "loss": 0.3076518972714742,
            "accuracy": 0.9316666722297668,
            "f1": 0.8982350872935911
         },
         "eval_metrics_server": {}
      }
   ]
}