{
   "info": {
      "strategy": "FedAvg",
      "seed": 130,
      "sampling_seed": 130,
      "fraction_train": 0.75,
      "fraction_evaluate": 0.75,
      "local_epochs": 2,
      "num_rounds": 60,
      "num_clients": 5,
      "eta_l": 0.35,
      "iid": false,
      "alpha": 1.8,
      "training_mode": "noiseless",
      "nshots": null,
      "model_type": "hybrid"
   },
   "rounds": [
      {
         "round": 0,
         "train_metrics": {},
         "eval_metrics_client": {},
         "eval_metrics_server": {
            "accuracy": 0.18000000715255737,
            "loss": 0.9450787305831909,
            "f1_score": 0.15254237288135594
         }
      },
      {
         "round": 1,
         "train_metrics": {
            "train_loss": 0.701250857173844,
            "train_acc": 0.5302013296808973,
            "train_f1": 0.34501014098140254
         },
         "eval_metrics_client": {
            "loss": 0.6506930192311604,
            "accuracy": 0.7849999864896138,
            "f1": 0.4396094900943292
         },
         "eval_metrics_server": {
            "accuracy": 0.8149999976158142,
            "loss": 0.6458050608634949,
            "f1_score": 0.47439448824490377
         }
      },
      {
         "round": 2,
         "train_metrics": {
            "train_loss": 0.4518221469681247,
            "train_acc": 0.7647058960681967,
            "train_f1": 0.426993440674015
         },
         "eval_metrics_client": {
            "loss": 0.45104317863782245,
            "accuracy": 0.7999999920527139,
            "f1": 0.44433379078912305
         },
         "eval_metrics_server": {
            "accuracy": 0.8199999928474426,
            "loss": 0.41846129298210144,
            "f1_score": 0.45054945054945056
         }
      },
      {
         "round": 3,
         "train_metrics": {
            "train_loss": 0.236547535172835,
            "train_acc": 0.9385026742749035,
            "train_f1": 0.7410418318674825
         },
         "eval_metrics_client": {
            "loss": 0.31092387437820435,
            "accuracy": 0.8133333524068196,
            "f1": 0.5299393143877741
         },
         "eval_metrics_server": {
            "accuracy": 0.8199999928474426,
            "loss": 0.2824871242046356,
            "f1_score": 0.45054945054945056
         }
      },
      {
         "round": 4,
         "train_metrics": {
            "train_loss": 0.1352763975896116,
            "train_acc": 0.9671361663251974,
            "train_f1": 0.9035355911835792
         },
         "eval_metrics_client": {
            "loss": 0.1823151558637619,
            "accuracy": 0.9416666626930237,
            "f1": 0.9068754646541433
         },
         "eval_metrics_server": {
            "accuracy": 0.9599999785423279,
            "loss": 0.17450645565986633,
            "f1_score": 0.929128277817151
         }
      },
      {
         "round": 5,
         "train_metrics": {
            "train_loss": 0.1460454901243634,
            "train_acc": 0.9618320526512525,
            "train_f1": 0.9490771044178093
         },
         "eval_metrics_client": {
            "loss": 0.14991310238838196,
            "accuracy": 0.9550000031789143,
            "f1": 0.9347646729032962
         },
         "eval_metrics_server": {
            "accuracy": 0.9449999928474426,
            "loss": 0.16622449457645416,
            "f1_score": 0.9097435897435897
         }
      },
      {
         "round": 6,
         "train_metrics": {
            "train_loss": 0.17266419734514132,
            "train_acc": 0.939597307035587,
            "train_f1": 0.9390930739874681
         },
         "eval_metrics_client": {
            "loss": 0.15950685242811838,
            "accuracy": 0.924999992052714,
            "f1": 0.892101974742931
         },
         "eval_metrics_server": {
            "accuracy": 0.9100000262260437,
            "loss": 0.19225944578647614,
            "f1_score": 0.864376130198915
         }
      },
      {
         "round": 7,
         "train_metrics": {
            "train_loss": 0.11098056494273979,
            "train_acc": 0.9550172995943511,
            "train_f1": 0.9294249332177932
         },
         "eval_metrics_client": {
            "loss": 0.1359778791666031,
            "accuracy": 0.9383333325386047,
            "f1": 0.9020027244100979
         },
         "eval_metrics_server": {
            "accuracy": 0.9700000286102295,
            "loss": 0.13177509605884552,
            "f1_score": 0.948051948051948
         }
      },
      {
         "round": 8,
         "train_metrics": {
            "train_loss": 0.07254294592215371,
            "train_acc": 0.9786096210466986,
            "train_f1": 0.9501550063278312
         },
         "eval_metrics_client": {
            "loss": 0.12741063038508096,
            "accuracy": 0.9566666483879089,
            "f1": 0.9290086651315665
         },
         "eval_metrics_server": {
            "accuracy": 0.9649999737739563,
            "loss": 0.12738387286663055,
            "f1_score": 0.9387013441919523
         }
      },
      {
         "round": 9,
         "train_metrics": {
            "train_loss": 0.08231385812857109,
            "train_acc": 0.9741783959205161,
            "train_f1": 0.9490696566292839
         },
         "eval_metrics_client": {
            "loss": 0.11689367393652597,
            "accuracy": 0.9633333285649617,
            "f1": 0.9438778672050798
         },
         "eval_metrics_server": {
            "accuracy": 0.9549999833106995,
            "loss": 0.12342360615730286,
            "f1_score": 0.9229419067597071
         }
      },
      {
         "round": 10,
         "train_metrics": {
            "train_loss": 0.10976668440705346,
            "train_acc": 0.9732824336481458,
            "train_f1": 0.9605893663152227
         },
         "eval_metrics_client": {
            "loss": 0.12499643117189407,
            "accuracy": 0.9483333230018616,
            "f1": 0.9254351592440673
         },
         "eval_metrics_server": {
            "accuracy": 0.925000011920929,
            "loss": 0.17074838280677795,
            "f1_score": 0.8816988051579321
         }
      },
      {
         "round": 11,
         "train_metrics": {
            "train_loss": 0.13374952464157608,
            "train_acc": 0.966442943019355,
            "train_f1": 0.9660319255907492
         },
         "eval_metrics_client": {
            "loss": 0.14730583628018695,
            "accuracy": 0.9283333420753479,
            "f1": 0.8951095498241579
         },
         "eval_metrics_server": {
            "accuracy": 0.9100000262260437,
            "loss": 0.19646264612674713,
            "f1_score": 0.864376130198915
         }
      },
      {
         "round": 12,
         "train_metrics": {
            "train_loss": 0.09972556034353236,
            "train_acc": 0.9584774874073411,
            "train_f1": 0.9300710632345568
         },
         "eval_metrics_client": {
            "loss": 0.12871743738651276,
            "accuracy": 0.9483333230018616,
            "f1": 0.9162235981736129
         },
         "eval_metrics_server": {
            "accuracy": 0.9599999785423279,
            "loss": 0.1194893941283226,
            "f1_score": 0.929128277817151
         }
      },
      {
         "round": 13,
         "train_metrics": {
            "train_loss": 0.06767951920333878,
            "train_acc": 0.9705882199945297,
            "train_f1": 0.9329178108589873
         },
         "eval_metrics_client": {
            "loss": 0.11565850178400675,
            "accuracy": 0.9599999785423279,
            "f1": 0.9348374202875888
         },
         "eval_metrics_server": {
            "accuracy": 0.9649999737739563,
            "loss": 0.11358415335416794,
            "f1_score": 0.9387013441919523
         }
      },
      {
         "round": 14,
         "train_metrics": {
            "train_loss": 0.08004020396932177,
            "train_acc": 0.9624413120354844,
            "train_f1": 0.9193075312518786
         },
         "eval_metrics_client": {
            "loss": 0.10409587870041528,
            "accuracy": 0.9649999936421711,
            "f1": 0.9466104121505488
         },
         "eval_metrics_server": {
            "accuracy": 0.9599999785423279,
            "loss": 0.11092423647642136,
            "f1_score": 0.9322493224932249
         }
      },
      {
         "round": 15,
         "train_metrics": {
            "train_loss": 0.10459772677776771,
            "train_acc": 0.9541984537175594,
            "train_f1": 0.91323029113779
         },
         "eval_metrics_client": {
            "loss": 0.1325993686914444,
            "accuracy": 0.9433333277702332,
            "f1": 0.9189413047352413
         },
         "eval_metrics_server": {
            "accuracy": 0.9049999713897705,
            "loss": 0.20234081149101257,
            "f1_score": 0.8529354851193931
         }
      },
      {
         "round": 16,
         "train_metrics": {
            "train_loss": 0.13756324214111929,
            "train_acc": 0.9328859040401127,
            "train_f1": 0.9324781929479916
         },
         "eval_metrics_client": {
            "loss": 0.1592102398475011,
            "accuracy": 0.9316666722297668,
            "f1": 0.8998427886355411
         },
         "eval_metrics_server": {
            "accuracy": 0.8999999761581421,
            "loss": 0.22348494827747345,
            "f1_score": 0.8518737964745964
         }
      },
      {
         "round": 17,
         "train_metrics": {
            "train_loss": 0.1005721257941516,
            "train_acc": 0.9446366680947141,
            "train_f1": 0.8996954154047581
         },
         "eval_metrics_client": {
            "loss": 0.1358714426557223,
            "accuracy": 0.9449999928474426,
            "f1": 0.9102476872000339
         },
         "eval_metrics_server": {
            "accuracy": 0.9599999785423279,
            "loss": 0.12060566991567612,
            "f1_score": 0.929128277817151
         }
      },
      {
         "round": 18,
         "train_metrics": {
            "train_loss": 0.06824648050547955,
            "train_acc": 0.9545454550235667,
            "train_f1": 0.8862792931810977
         },
         "eval_metrics_client": {
            "loss": 0.11324930687745412,
            "accuracy": 0.9583333134651184,
            "f1": 0.9309644615446051
         },
         "eval_metrics_server": {
            "accuracy": 0.9649999737739563,
            "loss": 0.10776074230670929,
            "f1_score": 0.9387013441919523
         }
      },
      {
         "round": 19,
         "train_metrics": {
            "train_loss": 0.08341501437949561,
            "train_acc": 0.9507042197554324,
            "train_f1": 0.8868116439566316
         },
         "eval_metrics_client": {
            "loss": 0.1002177894115448,
            "accuracy": 0.9633333285649617,
            "f1": 0.9443095300335986
         },
         "eval_metrics_server": {
            "accuracy": 0.9649999737739563,
            "loss": 0.10526657104492188,
            "f1_score": 0.9400659274797722
         }
      },
      {
         "round": 20,
         "train_metrics": {
            "train_loss": 0.10910915327042589,
            "train_acc": 0.9465648895911587,
            "train_f1": 0.8922452168397386
         },
         "eval_metrics_client": {
            "loss": 0.14495968321959177,
            "accuracy": 0.9433333277702332,
            "f1": 0.9192329984162687
         },
         "eval_metrics_server": {
            "accuracy": 0.9049999713897705,
            "loss": 0.23119577765464783,
            "f1_score": 0.8529354851193931
         }
      },
      {
         "round": 21,
         "train_metrics": {
            "train_loss": 0.15124045364685493,
            "train_acc": 0.9328859040401127,
            "train_f1": 0.9324781929479916
         },
         "eval_metrics_client": {
            "loss": 0.16777969896793365,
            "accuracy": 0.9283333420753479,
            "f1": 0.8955785473446518
         },
         "eval_metrics_server": {
            "accuracy": 0.8999999761581421,
            "loss": 0.23899784684181213,
            "f1_score": 0.8518737964745964
         }
      },
      {
         "round": 22,
         "train_metrics": {
            "train_loss": 0.10579628282018196,
            "train_acc": 0.9480968755009265,
            "train_f1": 0.9031449577761332
         },
         "eval_metrics_client": {
            "loss": 0.14505173762639362,
            "accuracy": 0.9416666626930237,
            "f1": 0.9043765131340987
         },
         "eval_metrics_server": {
            "accuracy": 0.9549999833106995,
            "loss": 0.12515561282634735,
            "f1_score": 0.9193223073820089
         }
      },
      {
         "round": 23,
         "train_metrics": {
            "train_loss": 0.07446315672156972,
            "train_acc": 0.9518716556821916,
            "train_f1": 0.8792407993798368
         },
         "eval_metrics_client": {
            "loss": 0.1181282326579094,
            "accuracy": 0.9599999785423279,
            "f1": 0.9332203976318258
         },
         "eval_metrics_server": {
            "accuracy": 0.9599999785423279,
            "loss": 0.10804590582847595,
            "f1_score": 0.929128277817151
         }
      },
      {
         "round": 24,
         "train_metrics": {
            "train_loss": 0.08806168178495072,
            "train_acc": 0.9507042197554324,
            "train_f1": 0.8868116439566316
         },
         "eval_metrics_client": {
            "loss": 0.10052567472060521,
            "accuracy": 0.9633333285649617,
            "f1": 0.9436757876355022
         },
         "eval_metrics_server": {
            "accuracy": 0.9700000286102295,
            "loss": 0.10221925377845764,
            "f1_score": 0.948051948051948
         }
      },
      {
         "round": 25,
         "train_metrics": {
            "train_loss": 0.11503647708704981,
            "train_acc": 0.9427480959255277,
            "train_f1": 0.8884196149607015
         },
         "eval_metrics_client": {
            "loss": 0.14999095102151233,
            "accuracy": 0.9433333277702332,
            "f1": 0.9190500075731227
         },
         "eval_metrics_server": {
            "accuracy": 0.9049999713897705,
            "loss": 0.23922477662563324,
            "f1_score": 0.8529354851193931
         }
      },
      {
         "round": 26,
         "train_metrics": {
            "train_loss": 0.16072939009198514,
            "train_acc": 0.946308716031529,
            "train_f1": 0.945944304412524
         },
         "eval_metrics_client": {
            "loss": 0.1672268857558568,
            "accuracy": 0.9266666769981384,
            "f1": 0.8920650496103812
         },
         "eval_metrics_server": {
            "accuracy": 0.9049999713897705,
            "loss": 0.23658689856529236,
            "f1_score": 0.858076563958917
         }
      },
      {
         "round": 27,
         "train_metrics": {
            "train_loss": 0.10858640953779519,
            "train_acc": 0.9480968755009265,
            "train_f1": 0.9031449577761332
         },
         "eval_metrics_client": {
            "loss": 0.14891185363133747,
            "accuracy": 0.9399999976158142,
            "f1": 0.9009290640243361
         },
         "eval_metrics_server": {
            "accuracy": 0.9549999833106995,
            "loss": 0.12743450701236725,
            "f1_score": 0.9193223073820089
         }
      },
      {
         "round": 28,
         "train_metrics": {
            "train_loss": 0.07558113064098457,
            "train_acc": 0.9518716556821916,
            "train_f1": 0.8792407993798368
         },
         "eval_metrics_client": {
            "loss": 0.12011007964611053,
            "accuracy": 0.9599999785423279,
            "f1": 0.9332203976318258
         },
         "eval_metrics_server": {
            "accuracy": 0.9599999785423279,
            "loss": 0.10824955254793167,
            "f1_score": 0.929128277817151
         }
      },
      {
         "round": 29,
         "train_metrics": {
            "train_loss": 0.0905954347774878,
            "train_acc": 0.9507042197554324,
            "train_f1": 0.8868116439566316
         },
         "eval_metrics_client": {
            "loss": 0.10139312346776326,
            "accuracy": 0.9633333285649617,
            "f1": 0.9431657924782161
         },
         "eval_metrics_server": {
            "accuracy": 0.9700000286102295,
            "loss": 0.10104969143867493,
            "f1_score": 0.948051948051948
         }
      },
      {
         "round": 30,
         "train_metrics": {
            "train_loss": 0.12188177311257484,
            "train_acc": 0.9465648895911587,
            "train_f1": 0.8922452168397386
         },
         "eval_metrics_client": {
            "loss": 0.1546671042839686,
            "accuracy": 0.9416666626930237,
            "f1": 0.9165886755744861
         },
         "eval_metrics_server": {
            "accuracy": 0.8999999761581421,
            "loss": 0.2450859695672989,
            "f1_score": 0.84375
         }
      },
      {
         "round": 31,
         "train_metrics": {
            "train_loss": 0.1665033379093199,
            "train_acc": 0.953020125027471,
            "train_f1": 0.9526453885632726
         },
         "eval_metrics_client": {
            "loss": 0.1644010990858078,
            "accuracy": 0.9300000071525574,
            "f1": 0.8964482092111825
         },
         "eval_metrics_server": {
            "accuracy": 0.8999999761581421,
            "loss": 0.23069366812705994,
            "f1_score": 0.8493068113321278
         }
      },
      {
         "round": 32,
         "train_metrics": {
            "train_loss": 0.10953119470916328,
            "train_acc": 0.9480968755009265,
            "train_f1": 0.9031449577761332
         },
         "eval_metrics_client": {
            "loss": 0.1503962179025014,
            "accuracy": 0.9399999976158142,
            "f1": 0.901178168601433
         },
         "eval_metrics_server": {
            "accuracy": 0.9549999833106995,
            "loss": 0.12859295308589935,
            "f1_score": 0.9193223073820089
         }
      },
      {
         "round": 33,
         "train_metrics": {
            "train_loss": 0.07424098282854291,
            "train_acc": 0.9518716556821916,
            "train_f1": 0.8792407993798368
         },
         "eval_metrics_client": {
            "loss": 0.12044975658257802,
            "accuracy": 0.9599999785423279,
            "f1": 0.9332203976318258
         },
         "eval_metrics_server": {
            "accuracy": 0.9599999785423279,
            "loss": 0.10842912644147873,
            "f1_score": 0.929128277817151
         }
      },
      {
         "round": 34,
         "train_metrics": {
            "train_loss": 0.09025344152910678,
            "train_acc": 0.9483567996763846,
            "train_f1": 0.8811077842974675
         },
         "eval_metrics_client": {
            "loss": 0.10157829523086548,
            "accuracy": 0.9616666634877522,
            "f1": 0.9407264124811048
         },
         "eval_metrics_server": {
            "accuracy": 0.9700000286102295,
            "loss": 0.10094672441482544,
            "f1_score": 0.948051948051948
         }
      },
      {
         "round": 35,
         "train_metrics": {
            "train_loss": 0.12583804200961982,
            "train_acc": 0.9465648895911587,
            "train_f1": 0.8922452168397386
         },
         "eval_metrics_client": {
            "loss": 0.1597892294327418,
            "accuracy": 0.9350000023841858,
            "f1": 0.9070536536560432
         },
         "eval_metrics_server": {
            "accuracy": 0.8999999761581421,
            "loss": 0.25138795375823975,
            "f1_score": 0.84375
         }
      },
      {
         "round": 36,
         "train_metrics": {
            "train_loss": 0.17027405887775507,
            "train_acc": 0.939597307035587,
            "train_f1": 0.9392174071487139
         },
         "eval_metrics_client": {
            "loss": 0.1624840795993805,
            "accuracy": 0.9300000071525574,
            "f1": 0.8964482092111825
         },
         "eval_metrics_server": {
            "accuracy": 0.8999999761581421,
            "loss": 0.22669512033462524,
            "f1_score": 0.8493068113321278
         }
      },
      {
         "round": 37,
         "train_metrics": {
            "train_loss": 0.1100653119983903,
            "train_acc": 0.9515570829071387,
            "train_f1": 0.9065971248064675
         },
         "eval_metrics_client": {
            "loss": 0.15067829191684723,
            "accuracy": 0.9399999976158142,
            "f1": 0.901178168601433
         },
         "eval_metrics_server": {
            "accuracy": 0.9549999833106995,
            "loss": 0.12904050946235657,
            "f1_score": 0.9193223073820089
         }
      },
      {
         "round": 38,
         "train_metrics": {
            "train_loss": 0.07295145004002764,
            "train_acc": 0.9518716556821916,
            "train_f1": 0.8792407993798368
         },
         "eval_metrics_client": {
            "loss": 0.12079638242721558,
            "accuracy": 0.9583333134651184,
            "f1": 0.9309644615446051
         },
         "eval_metrics_server": {
            "accuracy": 0.9599999785423279,
            "loss": 0.10875807702541351,
            "f1_score": 0.929128277817151
         }
      },
      {
         "round": 39,
         "train_metrics": {
            "train_loss": 0.08791288546082235,
            "train_acc": 0.9483567996763846,
            "train_f1": 0.8811077842974675
         },
         "eval_metrics_client": {
            "loss": 0.1013060212135315,
            "accuracy": 0.9633333285649617,
            "f1": 0.9436757876355022
         },
         "eval_metrics_server": {
            "accuracy": 0.9700000286102295,
            "loss": 0.1011526882648468,
            "f1_score": 0.948051948051948
         }
      },
      {
         "round": 40,
         "train_metrics": {
            "train_loss": 0.12732012577419907,
            "train_acc": 0.9427480920580507,
            "train_f1": 0.8829710022794185
         },
         "eval_metrics_client": {
            "loss": 0.16413559516270954,
            "accuracy": 0.9350000023841858,
            "f1": 0.9070536536560432
         },
         "eval_metrics_server": {
            "accuracy": 0.8949999809265137,
            "loss": 0.256661981344223,
            "f1_score": 0.837455009868803
         }
      },
      {
         "round": 41,
         "train_metrics": {
            "train_loss": 0.1716100310810927,
            "train_acc": 0.939597307035587,
            "train_f1": 0.9392174071487139
         },
         "eval_metrics_client": {
            "loss": 0.16062501569588977,
            "accuracy": 0.9333333373069763,
            "f1": 0.9007063600929925
         },
         "eval_metrics_server": {
            "accuracy": 0.9049999713897705,
            "loss": 0.22291356325149536,
            "f1_score": 0.8555737144160238
         }
      },
      {
         "round": 42,
         "train_metrics": {
            "train_loss": 0.11062393817288273,
            "train_acc": 0.9515570829071387,
            "train_f1": 0.9065971248064675
         },
         "eval_metrics_client": {
            "loss": 0.15028362969557443,
            "accuracy": 0.9399999976158142,
            "f1": 0.901178168601433
         },
         "eval_metrics_server": {
            "accuracy": 0.9549999833106995,
            "loss": 0.12887489795684814,
            "f1_score": 0.9193223073820089
         }
      },
      {
         "round": 43,
         "train_metrics": {
            "train_loss": 0.07221948777453972,
            "train_acc": 0.9518716556821916,
            "train_f1": 0.8792407993798368
         },
         "eval_metrics_client": {
            "loss": 0.12097870806852976,
            "accuracy": 0.9583333134651184,
            "f1": 0.9309644615446051
         },
         "eval_metrics_server": {
            "accuracy": 0.9599999785423279,
            "loss": 0.10896628350019455,
            "f1_score": 0.929128277817151
         }
      },
      {
         "round": 44,
         "train_metrics": {
            "train_loss": 0.08559679831314802,
            "train_acc": 0.9507042197554324,
            "train_f1": 0.8868116439566316
         },
         "eval_metrics_client": {
            "loss": 0.10163804143667221,
            "accuracy": 0.9616666634877522,
            "f1": 0.9414198515482814
         },
         "eval_metrics_server": {
            "accuracy": 0.9700000286102295,
            "loss": 0.10164088010787964,
            "f1_score": 0.948051948051948
         }
      },
      {
         "round": 45,
         "train_metrics": {
            "train_loss": 0.1266994430025813,
            "train_acc": 0.9541984730549441,
            "train_f1": 0.894394878445661
         },
         "eval_metrics_client": {
            "loss": 0.1644619256258011,
            "accuracy": 0.9350000023841858,
            "f1": 0.9072633054252839
         },
         "eval_metrics_server": {
            "accuracy": 0.8949999809265137,
            "loss": 0.25884944200515747,
            "f1_score": 0.837455009868803
         }
      },
      {
         "round": 46,
         "train_metrics": {
            "train_loss": 0.17334418374214344,
            "train_acc": 0.939597307035587,
            "train_f1": 0.9392174071487139
         },
         "eval_metrics_client": {
            "loss": 0.15942858159542084,
            "accuracy": 0.9333333373069763,
            "f1": 0.9007063600929925
         },
         "eval_metrics_server": {
            "accuracy": 0.9049999713897705,
            "loss": 0.2211698591709137,
            "f1_score": 0.8555737144160238
         }
      },
      {
         "round": 47,
         "train_metrics": {
            "train_loss": 0.11112687291866476,
            "train_acc": 0.9480968755009265,
            "train_f1": 0.9031449577761332
         },
         "eval_metrics_client": {
            "loss": 0.1501552015542984,
            "accuracy": 0.9399999976158142,
            "f1": 0.901178168601433
         },
         "eval_metrics_server": {
            "accuracy": 0.9549999833106995,
            "loss": 0.12868094444274902,
            "f1_score": 0.9193223073820089
         }
      },
      {
         "round": 48,
         "train_metrics": {
            "train_loss": 0.07151068983446951,
            "train_acc": 0.9518716556821916,
            "train_f1": 0.8792407993798368
         },
         "eval_metrics_client": {
            "loss": 0.12104561428229013,
            "accuracy": 0.9599999785423279,
            "f1": 0.9344234366282094
         },
         "eval_metrics_server": {
            "accuracy": 0.9599999785423279,
            "loss": 0.10902334004640579,
            "f1_score": 0.929128277817151
         }
      },
      {
         "round": 49,
         "train_metrics": {
            "train_loss": 0.08337632975218953,
            "train_acc": 0.9507042197554324,
            "train_f1": 0.8868116439566316
         },
         "eval_metrics_client": {
            "loss": 0.10212133824825287,
            "accuracy": 0.9616666634877522,
            "f1": 0.9414198515482814
         },
         "eval_metrics_server": {
            "accuracy": 0.9700000286102295,
            "loss": 0.10207171738147736,
            "f1_score": 0.948051948051948
         }
      },
      {
         "round": 50,
         "train_metrics": {
            "train_loss": 0.12355238483296281,
            "train_acc": 0.950381679389313,
            "train_f1": 0.8905869537442619
         },
         "eval_metrics_client": {
            "loss": 0.16108774145444232,
            "accuracy": 0.9366666674613953,
            "f1": 0.9099923740626924
         },
         "eval_metrics_server": {
            "accuracy": 0.8949999809265137,
            "loss": 0.25821083784103394,
            "f1_score": 0.837455009868803
         }
      },
      {
         "round": 51,
         "train_metrics": {
            "train_loss": 0.1752561399994505,
            "train_acc": 0.946308716031529,
            "train_f1": 0.945944304412524
         },
         "eval_metrics_client": {
            "loss": 0.15953703721364337,
            "accuracy": 0.9316666722297668,
            "f1": 0.8985896737213463
         },
         "eval_metrics_server": {
            "accuracy": 0.9049999713897705,
            "loss": 0.2223598062992096,
            "f1_score": 0.8555737144160238
         }
      },
      {
         "round": 52,
         "train_metrics": {
            "train_loss": 0.11177603054016833,
            "train_acc": 0.9480968755009265,
            "train_f1": 0.9031449577761332
         },
         "eval_metrics_client": {
            "loss": 0.15042954683303833,
            "accuracy": 0.9416666626930237,
            "f1": 0.9040147462704752
         },
         "eval_metrics_server": {
            "accuracy": 0.9549999833106995,
            "loss": 0.1286260038614273,
            "f1_score": 0.9193223073820089
         }
      },
      {
         "round": 53,
         "train_metrics": {
            "train_loss": 0.0710476960443489,
            "train_acc": 0.9545454550235667,
            "train_f1": 0.8862792931810977
         },
         "eval_metrics_client": {
            "loss": 0.12102028230826059,
            "accuracy": 0.9599999785423279,
            "f1": 0.9344234366282094
         },
         "eval_metrics_server": {
            "accuracy": 0.9599999785423279,
            "loss": 0.10897201299667358,
            "f1_score": 0.929128277817151
         }
      },
      {
         "round": 54,
         "train_metrics": {
            "train_loss": 0.08209802861953125,
            "train_acc": 0.9507042197554324,
            "train_f1": 0.8868116439566316
         },
         "eval_metrics_client": {
            "loss": 0.10231130818525949,
            "accuracy": 0.9616666634877522,
            "f1": 0.9414198515482814
         },
         "eval_metrics_server": {
            "accuracy": 0.9700000286102295,
            "loss": 0.10221105813980103,
            "f1_score": 0.948051948051948
         }
      },
      {
         "round": 55,
         "train_metrics": {
            "train_loss": 0.120534502259837,
            "train_acc": 0.954198476922421,
            "train_f1": 0.8998611683045821
         },
         "eval_metrics_client": {
            "loss": 0.1575329601764679,
            "accuracy": 0.9399999976158142,
            "f1": 0.9149172062622579
         },
         "eval_metrics_server": {
            "accuracy": 0.8949999809265137,
            "loss": 0.25615066289901733,
            "f1_score": 0.8403709475124472
         }
      },
      {
         "round": 56,
         "train_metrics": {
            "train_loss": 0.17636757017505117,
            "train_acc": 0.9597315340234129,
            "train_f1": 0.9593361116862755
         },
         "eval_metrics_client": {
            "loss": 0.15971987942854562,
            "accuracy": 0.9316666722297668,
            "f1": 0.8985896737213463
         },
         "eval_metrics_server": {
            "accuracy": 0.9100000262260437,
            "loss": 0.22345325350761414,
            "f1_score": 0.864376130198915
         }
      },
      {
         "round": 57,
         "train_metrics": {
            "train_loss": 0.11213619933273246,
            "train_acc": 0.9480968755009265,
            "train_f1": 0.9031449577761332
         },
         "eval_metrics_client": {
            "loss": 0.15054885049661,
            "accuracy": 0.9416666626930237,
            "f1": 0.9040147462704752
         },
         "eval_metrics_server": {
            "accuracy": 0.9549999833106995,
            "loss": 0.12850113213062286,
            "f1_score": 0.9193223073820089
         }
      },
      {
         "round": 58,
         "train_metrics": {
            "train_loss": 0.07096054376845468,
            "train_acc": 0.9518716556821916,
            "train_f1": 0.8792407993798368
         },
         "eval_metrics_client": {
            "loss": 0.12090153495470682,
            "accuracy": 0.9599999785423279,
            "f1": 0.9344234366282094
         },
         "eval_metrics_server": {
            "accuracy": 0.9599999785423279,
            "loss": 0.10891019552946091,
            "f1_score": 0.929128277817151
         }
      },
      {
         "round": 59,
         "train_metrics": {
            "train_loss": 0.08181995061344446,
            "train_acc": 0.9507042197554324,
            "train_f1": 0.8868116439566316
         },
         "eval_metrics_client": {
            "loss": 0.10231700291236241,
            "accuracy": 0.9616666634877522,
            "f1": 0.9414198515482814
         },
         "eval_metrics_server": {
            "accuracy": 0.9700000286102295,
            "loss": 0.10223741829395294,
            "f1_score": 0.948051948051948
         }
      },
      {
         "round": 60,
         "train_metrics": {
            "train_loss": 0.11966001396494,
            "train_acc": 0.954198476922421,
            "train_f1": 0.8998611683045821
         },
         "eval_metrics_client": {
            "loss": 0.1564201960961024,
            "accuracy": 0.9399999976158142,
            "f1": 0.9149172062622579
         },
         "eval_metrics_server": {
            "accuracy": 0.8949999809265137,
            "loss": 0.2553298771381378,
            "f1_score": 0.8403709475124472
         }
      }
   ]
}